frostmark/__init__.py
frostmark/__main__.py
frostmark/common.py
frostmark/db.py
frostmark/db_base.py
frostmark/models.py
frostmark/parser.py
frostmark/profiles.py
frostmark/profiling.py
frostmark/core/__init__.py
frostmark/core/console/__init__.py
frostmark/core/gui/__init__.py
frostmark/core/gui/react/__init__.py
frostmark/core/gui/react/build/asset-manifest.json
frostmark/core/gui/react/build/index.html
frostmark/core/gui/react/build/manifest.json
frostmark/core/gui/react/build/precache-manifest.d399d9c3527cfa96f52886d8250e274e.js
frostmark/core/gui/react/build/service-worker.js
frostmark/core/gui/react/build/static/css/2.654e7845.chunk.css
frostmark/core/gui/react/build/static/css/2.654e7845.chunk.css.map
frostmark/core/gui/react/build/static/css/main.51959fdd.chunk.css
frostmark/core/gui/react/build/static/css/main.51959fdd.chunk.css.map
frostmark/core/gui/react/build/static/js/2.aa570848.chunk.js
frostmark/core/gui/react/build/static/js/2.aa570848.chunk.js.map
frostmark/core/gui/react/build/static/js/main.d85dbd0f.chunk.js
frostmark/core/gui/react/build/static/js/main.d85dbd0f.chunk.js.map
frostmark/core/gui/react/build/static/js/runtime~main.a8a9905a.js
frostmark/core/gui/react/build/static/js/runtime~main.a8a9905a.js.map
frostmark/core/gui/react/build/static/media/fontawesome-webfont.674f50d2.eot
frostmark/core/gui/react/build/static/media/fontawesome-webfont.912ec66d.svg
frostmark/core/gui/react/build/static/media/fontawesome-webfont.af7ae505.woff2
frostmark/core/gui/react/build/static/media/fontawesome-webfont.b06871f2.ttf
frostmark/core/gui/react/build/static/media/fontawesome-webfont.fee66e71.woff
frostmark/editor/__init__.py
frostmark/exporter/__init__.py
frostmark/importer/__init__.py
frostmark/importer/chrome.py
frostmark/importer/firefox.py
frostmark/importer/opera.py
frostmark/tests/__init__.py
frostmark/tests/sample_chrome.json
frostmark/tests/sample_firefox.sqlite
frostmark/tests/sample_opera.json
frostmark/tests/test_common_tree.py
frostmark-0.1.0.dist-info/LICENSE.txt
frostmark-0.1.0.dist-info/METADATA
frostmark-0.1.0.dist-info/WHEEL
frostmark-0.1.0.dist-info/entry_points.txt
frostmark-0.1.0.dist-info/top_level.txt
frostmark-0.1.0.dist-info/RECORD
