Metadata-Version: 2.1
Name: frostmark
Version: 0.1.0
Summary: Frostmark - A simple bookmark manager.
Home-page: https://github.com/KeyWeeUsr/Frostmark
Author: Peter Badida
Author-email: keyweeusr@gmail.com
License: GNU AFFERO GENERAL PUBLIC LICENSE
Requires-Dist: ensure
Requires-Dist: sqlalchemy
Requires-Dist: anytree
Provides-Extra: ci
Requires-Dist: coveralls ; extra == 'ci'
Provides-Extra: dev
Requires-Dist: pycodestyle ; extra == 'dev'
Requires-Dist: pylint ; extra == 'dev'
Requires-Dist: coverage ; extra == 'dev'
Provides-Extra: doc
Requires-Dist: sphinx (>=1.8.1) ; extra == 'doc'
Provides-Extra: gui_react
Requires-Dist: flask ; extra == 'gui_react'
Provides-Extra: release
Requires-Dist: setuptools ; extra == 'release'
Requires-Dist: wheel ; extra == 'release'
Requires-Dist: pycodestyle ; extra == 'release'
Requires-Dist: pylint ; extra == 'release'
Requires-Dist: coverage ; extra == 'release'
Requires-Dist: coveralls ; extra == 'release'
Requires-Dist: sphinx (>=1.8.1) ; extra == 'release'
Requires-Dist: flask ; extra == 'release'
Requires-Dist: twine ; extra == 'release'
